QualityQueue/__init__.py
QualityQueue-1.0.0.dist-info/METADATA
QualityQueue-1.0.0.dist-info/WHEEL
QualityQueue-1.0.0.dist-info/top_level.txt
QualityQueue-1.0.0.dist-info/RECORD
