Metadata-Version: 2.1
Name: QualityQueue
Version: 1.0.0
Summary: Queue in python
Home-page: UNKNOWN
Author: Kellan Butler
Author-email: <kellanbutler52@gmail.com>
License: UNKNOWN
Keywords: python,queue
Platform: UNKNOWN
Classifier: Development Status :: 4 - Beta
Classifier: Intended Audience :: Developers
Classifier: Programming Language :: Python :: 3
Classifier: Operating System :: MacOS :: MacOS X
Classifier: Operating System :: Microsoft :: Windows
Classifier: Operating System :: POSIX :: Linux
